chak/__init__.py
chak/conversation.py
chak/exceptions.py
chak/message.py
chak/context/__init__.py
chak/context/strategies/__init__.py
chak/context/strategies/base.py
chak/context/strategies/fifo.py
chak/context/strategies/lru.py
chak/context/strategies/noop.py
chak/context/strategies/summarize.py
chak/mcp/__init__.py
chak/mcp/client.py
chak/mcp/manager.py
chak/mcp/server.py
chak/mcp/tool.py
chak/providers/__init__.py
chak/providers/types.py
chak/providers/llm/__init__.py
chak/providers/llm/anthropic.py
chak/providers/llm/azure.py
chak/providers/llm/baidu.py
chak/providers/llm/bailian.py
chak/providers/llm/base.py
chak/providers/llm/deepseek.py
chak/providers/llm/google.py
chak/providers/llm/iflytek.py
chak/providers/llm/minimax.py
chak/providers/llm/mistral.py
chak/providers/llm/moonshot.py
chak/providers/llm/ollama.py
chak/providers/llm/openai.py
chak/providers/llm/siliconflow.py
chak/providers/llm/tencent.py
chak/providers/llm/vllm.py
chak/providers/llm/volcengine.py
chak/providers/llm/xai.py
chak/providers/llm/zhipu.py
chak/server/__init__.py
chak/server/app.py
chak/server/config.py
chak/server/playground.html
chak/server/schemas.py
chak/server/websocket.py
chak/utils/__init__.py
chak/utils/logger.py
chak/utils/model_info.py
chak/utils/models.py
chak/utils/uri.py
chakpy-0.1.4.dist-info/licenses/LICENSE
examples/__init__.py
examples/mcp_chat_http.py
examples/mcp_chat_sse.py
examples/mcp_chat_stdio.py
examples/my_calculator_mcp_server.py
examples/simple_chat_bailian_qwen.py
examples/simple_chat_ollama_qwen.py
examples/simple_chat_openai_gpt4.py
examples/simple_gateway_server.py
examples/strategy_chat_fifo.py
examples/strategy_chat_lru.py
examples/strategy_chat_summarization.py
chakpy-0.1.4.dist-info/METADATA
chakpy-0.1.4.dist-info/WHEEL
chakpy-0.1.4.dist-info/top_level.txt
chakpy-0.1.4.dist-info/RECORD
