Metadata-Version: 2.4
Name: chakpy
Version: 0.1.4
Summary: A simple, yet elegant, LLM API routing library
Author: Chak Contributors
License: MIT
Project-URL: Homepage, https://github.com/zhixiangxue/chak-ai
Project-URL: Repository, https://github.com/zhixiangxue/chak-ai
Project-URL: Documentation, https://github.com/zhixiangxue/chak-ai/blob/main/README.md
Project-URL: Bug Tracker, https://github.com/zhixiangxue/chak-ai/issues
Keywords: llm,openai,api,routing,chatbot,ai
Classifier: Development Status :: 4 - Beta
Classifier: Intended Audience :: Developers
Classifier: License :: OSI Approved :: MIT License
Classifier: Programming Language :: Python :: 3
Classifier: Programming Language :: Python :: 3.8
Classifier: Programming Language :: Python :: 3.9
Classifier: Programming Language :: Python :: 3.10
Classifier: Programming Language :: Python :: 3.11
Classifier: Programming Language :: Python :: 3.12
Classifier: Topic :: Software Development :: Libraries :: Python Modules
Classifier: Topic :: Scientific/Engineering :: Artificial Intelligence
Requires-Python: >=3.8
License-File: LICENSE
Requires-Dist: openai>=1.0.0
Requires-Dist: pydantic>=2.0.0
Requires-Dist: httpx>=0.24.0
Requires-Dist: tiktoken>=0.5.0
Requires-Dist: loguru>=0.7.0
Provides-Extra: server
Requires-Dist: fastapi>=0.104.0; extra == "server"
Requires-Dist: uvicorn>=0.24.0; extra == "server"
Requires-Dist: websockets>=12.0; extra == "server"
Requires-Dist: pyyaml>=6.0; extra == "server"
Provides-Extra: all
Requires-Dist: fastapi>=0.104.0; extra == "all"
Requires-Dist: uvicorn>=0.24.0; extra == "all"
Requires-Dist: websockets>=12.0; extra == "all"
Requires-Dist: pyyaml>=6.0; extra == "all"
Dynamic: license-file
